SinglePortRAM.v
module Single_Port_RAM(clk,rst,Wr_Rd,valid,ADDR,WDATA,RDATA,ready);
  
  parameter N = 4;  //No. of Address Lines
  parameter D = 16; //Depth of Memory
  parameter W = 8;  //Width of Memory
  
  input clk,rst,Wr_Rd,valid;
  input [N-1:0] ADDR;
  input [W-1:0] WDATA;
  output[W-1:0] RDATA;
  output ready;
  
  reg [W-1:0] temp_read;
  reg [W-1:0] mem [D-1:0];
  integer i;
  
  always@(posedge clk)
    begin
      if(valid)
        begin
      if(!rst) //active low reset
        begin
          
          for(i = 0;i<D;i=i+1)
            mem[i] = 0;
        end
      else if(Wr_Rd && valid)
        mem[ADDR] = WDATA;
        end
    end 
  
  always@(posedge clk)
    if(!Wr_Rd && valid)
        temp_read = mem[ADDR];
  
  assign ready = (!Wr_Rd)&&valid;
  assign RDATA = (ready==1)?temp_read:16'bx;
  
endmodule

SinglePortRAM_tb.v
module tb;
  
  reg clk,rst,Wr_Rd,valid;
  reg [7:0] WDATA;
  reg [3:0] ADDR;
  wire [7:0] RDATA;
  wire ready;
  
  Single_Port_RAM DUT (clk,rst,Wr_Rd,valid,ADDR,WDATA,RDATA,ready);
  
  initial begin
    rst = 0;
    clk = 0;
    forever
      #5 clk = ~clk;
  end
  
  initial begin
    $monitor("Time = %3t, clk=%0b, rst=%b,Wr_Rd=%b,valid=%b,ADDR=%b,WDATA=%b,RDATA=%b,ready=%b",$time,clk,rst,Wr_Rd,valid,ADDR,WDATA,RDATA,ready);
    
    valid=0; #10
    rst=1;
     
    Wr_Rd=1;//Write Data
    for(integer i=0;i<16;i=i+1) begin
      repeat(1) @(posedge clk)
        begin
          ADDR=i;
          WDATA = $random;
        end
    end
    
    Wr_Rd=0;//Read Data
    for(integer i=0;i<16;i=i+1) begin
      repeat(1) @(posedge clk)
        begin
          ADDR=i;
        end
    end
    
    #10
    valid=1;
     
    Wr_Rd=1;//Write Data
    for(integer i=0;i<16;i=i+1) begin
      repeat(1) @(posedge clk)
        begin
          ADDR=i;
          WDATA = $random;
        end
    end
    
    #10
    Wr_Rd=0;//Read Data
    for(integer i=0;i<16;i=i+1) begin
      repeat(1) @(posedge clk)
        begin
          ADDR=i;
        end
    end
    
	#10 $finish;
    
  end
  
  initial begin
    $dumpfile("wave.vcd");
    $dumpvars;
  end
  
endmodule

wave.vcd
$date
	Sun Jul  3 10:09:29 2022
$end

$version
	Synopsys VCS version Q-2020.03-SP1-1
$end

$timescale
	1ns
$end

$comment Csum: 1 ca2b4afb5b07b5c6 $end


$scope module tb $end
$var reg 1 ! clk $end
$var reg 1 " rst $end
$var reg 1 # Wr_Rd $end
$var reg 1 $ valid $end
$var reg 8 % WDATA [7:0] $end
$var reg 4 & ADDR [3:0] $end
$var wire 8 ' RDATA [7:0] $end
$var wire 1 ( ready $end
$var integer 32 ) i $end

$scope module DUT $end
$var wire 1 ! clk $end
$var wire 1 " rst $end
$var wire 1 # Wr_Rd $end
$var wire 1 $ valid $end
$var wire 4 & ADDR [3:0] $end
$var wire 8 % WDATA [7:0] $end
$var wire 8 ' RDATA [7:0] $end
$var wire 1 ( ready $end
$var reg 8 * temp_read [7:0] $end
$var integer 32 + i $end
$upscope $end

$upscope $end

$enddefinitions $end

#0
$dumpvars
x#
0!
0(
0"
0$
bxxxx &
bxxxxxxxxxxxxxxxxxxxxxxxxxxxxxxxx +
bxxxxxxxx '
bxxxxxxxx %
bxxxxxxxxxxxxxxxxxxxxxxxxxxxxxxxx )
bxxxxxxxx *
$end
#5
1!
#10
1"
1#
b00000000000000000000000000000000 )
0!
#15
1!
b0000 &
b00100100 %
b00000000000000000000000000000001 )
#20
0!
#25
1!
b0001 &
b10000001 %
b00000000000000000000000000000010 )
#30
0!
#35
1!
b0010 &
b00001001 %
b00000000000000000000000000000011 )
#40
0!
#45
1!
b0011 &
b01100011 %
b00000000000000000000000000000100 )
#50
0!
#55
1!
b0100 &
b00001101 %
b00000000000000000000000000000101 )
#60
0!
#65
1!
b0101 &
b10001101 %
b00000000000000000000000000000110 )
#70
0!
#75
1!
b0110 &
b01100101 %
b00000000000000000000000000000111 )
#80
0!
#85
1!
b0111 &
b00010010 %
b00000000000000000000000000001000 )
#90
0!
#95
1!
b1000 &
b00000001 %
b00000000000000000000000000001001 )
#100
0!
#105
1!
b1001 &
b00001101 %
b00000000000000000000000000001010 )
#110
0!
#115
1!
b1010 &
b01110110 %
b00000000000000000000000000001011 )
#120
0!
#125
1!
b1011 &
b00111101 %
b00000000000000000000000000001100 )
#130
0!
#135
1!
b1100 &
b11101101 %
b00000000000000000000000000001101 )
#140
0!
#145
1!
b1101 &
b10001100 %
b00000000000000000000000000001110 )
#150
0!
#155
1!
b1110 &
b11111001 %
b00000000000000000000000000001111 )
#160
0!
#165
1!
b1111 &
b11000110 %
b00000000000000000000000000010000 )
0#
b00000000000000000000000000000000 )
#170
0!
#175
1!
b0000 &
b00000000000000000000000000000001 )
#180
0!
#185
1!
b0001 &
b00000000000000000000000000000010 )
#190
0!
#195
1!
b0010 &
b00000000000000000000000000000011 )
#200
0!
#205
1!
b0011 &
b00000000000000000000000000000100 )
#210
0!
#215
1!
b0100 &
b00000000000000000000000000000101 )
#220
0!
#225
1!
b0101 &
b00000000000000000000000000000110 )
#230
0!
#235
1!
b0110 &
b00000000000000000000000000000111 )
#240
0!
#245
1!
b0111 &
b00000000000000000000000000001000 )
#250
0!
#255
1!
b1000 &
b00000000000000000000000000001001 )
#260
0!
#265
1!
b1001 &
b00000000000000000000000000001010 )
#270
0!
#275
1!
b1010 &
b00000000000000000000000000001011 )
#280
0!
#285
1!
b1011 &
b00000000000000000000000000001100 )
#290
0!
#295
1!
b1100 &
b00000000000000000000000000001101 )
#300
0!
#305
1!
b1101 &
b00000000000000000000000000001110 )
#310
0!
#315
1!
b1110 &
b00000000000000000000000000001111 )
#320
0!
#325
1!
b1111 &
b00000000000000000000000000010000 )
#330
0!
#335
1$
1(
1#
0(
b00000000000000000000000000000000 )
1!
b0000 &
b11000101 %
b00000000000000000000000000000001 )
#340
0!
#345
1!
b0001 &
b10101010 %
b00000000000000000000000000000010 )
#350
0!
#355
1!
b0010 &
b11100101 %
b00000000000000000000000000000011 )
#360
0!
#365
1!
b0011 &
b01110111 %
b00000000000000000000000000000100 )
#370
0!
#375
1!
b0100 &
b00010010 %
b00000000000000000000000000000101 )
#380
0!
#385
1!
b0101 &
b10001111 %
b00000000000000000000000000000110 )
#390
0!
#395
1!
b0110 &
b11110010 %
b00000000000000000000000000000111 )
#400
0!
#405
1!
b0111 &
b11001110 %
b00000000000000000000000000001000 )
#410
0!
#415
1!
b1000 &
b11101000 %
b00000000000000000000000000001001 )
#420
0!
#425
1!
b1001 &
b11000101 %
b00000000000000000000000000001010 )
#430
0!
#435
1!
b1010 &
b01011100 %
b00000000000000000000000000001011 )
#440
0!
#445
1!
b1011 &
b10111101 %
b00000000000000000000000000001100 )
#450
0!
#455
1!
b1100 &
b00101101 %
b00000000000000000000000000001101 )
#460
0!
#465
1!
b1101 &
b01100101 %
b00000000000000000000000000001110 )
#470
0!
#475
1!
b1110 &
b01100011 %
b00000000000000000000000000001111 )
#480
0!
#485
1!
b1111 &
b00001010 %
b00000000000000000000000000010000 )
#490
0!
#495
0#
1(
b00000000000000000000000000000000 )
1!
b0000 &
b00000000000000000000000000000001 )
b11000101 *
b11000101 '
#500
0!
#505
1!
b0001 &
b00000000000000000000000000000010 )
b10101010 *
b10101010 '
#510
0!
#515
1!
b0010 &
b00000000000000000000000000000011 )
b11100101 *
b11100101 '
#520
0!
#525
1!
b0011 &
b00000000000000000000000000000100 )
b01110111 *
b01110111 '
#530
0!
#535
1!
b0100 &
b00000000000000000000000000000101 )
b00010010 *
b00010010 '
#540
0!
#545
1!
b0101 &
b00000000000000000000000000000110 )
b10001111 *
b10001111 '
#550
0!
#555
1!
b0110 &
b00000000000000000000000000000111 )
b11110010 *
b11110010 '
#560
0!
#565
1!
b0111 &
b00000000000000000000000000001000 )
b11001110 *
b11001110 '
#570
0!
#575
1!
b1000 &
b00000000000000000000000000001001 )
b11101000 *
b11101000 '
#580
0!
#585
1!
b1001 &
b00000000000000000000000000001010 )
b11000101 *
b11000101 '
#590
0!
#595
1!
b1010 &
b00000000000000000000000000001011 )
b01011100 *
b01011100 '
#600
0!
#605
1!
b1011 &
b00000000000000000000000000001100 )
b10111101 *
b10111101 '
#610
0!
#615
1!
b1100 &
b00000000000000000000000000001101 )
b00101101 *
b00101101 '
#620
0!
#625
1!
b1101 &
b00000000000000000000000000001110 )
b01100101 *
b01100101 '
#630
0!
#635
1!
b1110 &
b00000000000000000000000000001111 )
b01100011 *
b01100011 '
#640
0!
#645
1!
b1111 &
b00000000000000000000000000010000 )
b00001010 *
b00001010 '
